tesscube/__init__.py
tesscube/config.py
tesscube/cube.py
tesscube/fits.py
tesscube/query.py
tesscube/utils.py
tesscube/wcs.py
tesscube-1.2.1.dist-info/LICENSE
tesscube-1.2.1.dist-info/METADATA
tesscube-1.2.1.dist-info/WHEEL
tesscube-1.2.1.dist-info/RECORD
