Metadata-Version: 2.3
Name: tesscube
Version: 1.2.1
Summary: 
License: MIT
Author: TESS Science Support Center
Author-email: tesshelp@bigbang.gsfc.nasa.gov
Requires-Python: >=3.9,<4.0
Classifier: License :: OSI Approved :: MIT License
Classifier: Programming Language :: Python :: 3
Classifier: Programming Language :: Python :: 3.9
Classifier: Programming Language :: Python :: 3.10
Classifier: Programming Language :: Python :: 3.11
Classifier: Programming Language :: Python :: 3.12
Classifier: Programming Language :: Python :: 3.13
Requires-Dist: aiobotocore (>=2.7.0,<3.0.0)
Requires-Dist: aiohttp (>=3.8.6,<4.0.0)
Requires-Dist: astropy (>=5.0)
Requires-Dist: asyncio (>=3.4.3,<4.0.0)
Requires-Dist: boto3 (>=1.0.0)
Requires-Dist: lkspacecraft (>=1.0.6,<2.0.0)
Requires-Dist: nest-asyncio (>=1.5.8,<2.0.0)
Requires-Dist: numpy (>=1.26.1)
Requires-Dist: rich (>=13.7.0,<14.0.0)
